pyatsimagebuilder/Dockerfile.template
pyatsimagebuilder/__init__.py
pyatsimagebuilder/askpass.py
pyatsimagebuilder/builder.py
pyatsimagebuilder/commands.py
pyatsimagebuilder/context.py
pyatsimagebuilder/docker-entrypoint.sh
pyatsimagebuilder/image.py
pyatsimagebuilder/main.py
pyatsimagebuilder/schema.py
pyatsimagebuilder/utils.py
pyats_image_builder-25.9.dist-info/LICENSE
pyats_image_builder-25.9.dist-info/METADATA
pyats_image_builder-25.9.dist-info/WHEEL
pyats_image_builder-25.9.dist-info/entry_points.txt
pyats_image_builder-25.9.dist-info/top_level.txt
pyats_image_builder-25.9.dist-info/RECORD
