Metadata-Version: 2.1
Name: pyats-image-builder
Version: 25.9
Summary: pyATS Docker image creation
Home-page: https://developer.cisco.com/docs/pyats/
Author: Cisco Systems Inc.
Author-email: pyats-support-ext@cisco.com
License: Cisco Systems, Inc. Cisco Confidential
Keywords: pyats cisco development packaging docker
Classifier: Development Status :: 5 - Production/Stable
Classifier: Environment :: Console
Classifier: Intended Audience :: Developers
Classifier: Intended Audience :: Telecommunications Industry
Classifier: Intended Audience :: Information Technology
Classifier: Intended Audience :: System Administrators
Classifier: License :: OSI Approved :: Apache Software License
Classifier: Operating System :: MacOS
Classifier: Operating System :: POSIX :: Linux
Classifier: Programming Language :: Python :: 3.7
Classifier: Programming Language :: Python :: 3.6
Classifier: Programming Language :: Python :: 3.5
Classifier: Programming Language :: Python :: 3 :: Only
Classifier: Programming Language :: Python :: Implementation :: CPython
Classifier: Topic :: Software Development :: Testing
Classifier: Topic :: Software Development :: Build Tools
Classifier: Topic :: Software Development :: Libraries
Classifier: Topic :: Software Development :: Libraries :: Python Modules
License-File: LICENSE
Requires-Dist: setuptools
Requires-Dist: pyyaml
Requires-Dist: requests
Requires-Dist: gitpython
Requires-Dist: docker
Requires-Dist: jsonschema
Requires-Dist: jinja2
